[
  {
    "docx": "http://www.cy.gov.tw/AP_HOME/Op_Upload/eDoc/調查報告/100/100000364徐許美鳳案調查意見上網.docx", 
    "describe": "洪委員昭男調查，據徐許美鳳等陳訴：臺北市政府工務局新建工程處辦理「復興北路穿越松山機場地下道工程」疑似設置不當，致渠子徐佳傑騎乘自行車失控摔落死亡；又於訴請國賠過程中，詎無鑑定單位願意協助鑑定，請求法院轉換舉證責任亦未獲接受，致遭判決駁回，涉有違失等情乙案之調查報告。....詳全文", 
    "reportLink": "", 
    "date": "100/08/04", 
    "pdf": "http://www.cy.gov.tw/AP_HOME/Op_Upload/eDoc/調查報告/100/100000364徐許美鳳案調查意見上網.pdf", 
    "id": "0990800747"
  }, 
  {
    "docx": "http://www.cy.gov.tw/AP_HOME/Op_Upload/eDoc/調查報告/100/100000356雞蛋產銷機制調查意見-公布.doc", 
    "describe": "李委員炳南、程委員仁宏調查︰據報載：國內物價持續上漲，惟雞蛋產地價格卻長期低迷不振，加上養雞飼料成本不斷增加，致養雞戶生存不易；另國內雞蛋市場價格長期由大盤商聯合運輸業者壟斷決定，蛋農及消費者之權益均未獲保障。究行政院農業委員會等相關主管機關，對於雞蛋等民生必需品之產銷制度、市場開拓、供需調查，及養雞戶之補助、休養、離養等輔導措施，有無具體規畫；相關管理機制、規範是否健全完備等情乙案之調查報告。....詳全文", 
    "reportLink": "http://www.cy.gov.tw/sp.asp?xdUrl=./di/edoc/eDocForm_Read.asp&ctNode=911&AP_Code=eDoc&Func_Code=t02&case_id=100000134", 
    "date": "100/08/03", 
    "pdf": "http://www.cy.gov.tw/AP_HOME/Op_Upload/eDoc/調查報告/100/100000356雞蛋產銷機制調查意見-公布.pdf", 
    "id": "1000800132"
  }, 
  {
    "docx": "http://www.cy.gov.tw/AP_HOME/Op_Upload/eDoc/調查報告/100/100000354違法檢驗調查報告(案由及意見)-上網版.doc", 
    "describe": "尹委員祚芊調查︰據報載，高雄市某婦產科診所於99年發生護士驗錯血導致孕婦喪命乙事；惟據醫事檢驗師法第12條規定，「輸血檢驗及血庫作業」屬醫事檢驗師業務，非以醫囑之名，要求護理人員違法。究上開診所是否長期皆為護理人員執行檢驗工作；高雄市政府衛生局有無善盡管理督導之責，是否怠忽職守，均有深入瞭解之必要乙案之調查報告。....詳全文", 
    "reportLink": "http://www.cy.gov.tw/sp.asp?xdUrl=./di/edoc/eDocForm_Read.asp&ctNode=911&AP_Code=eDoc&Func_Code=t02&case_id=100000136", 
    "date": "100/08/03", 
    "pdf": "http://www.cy.gov.tw/AP_HOME/Op_Upload/eDoc/調查報告/100/100000354違法檢驗調查報告(案由及意見)-上網版.pdf", 
    "id": "1000800133"
  }, 
  {
    "docx": "http://www.cy.gov.tw/AP_HOME/Op_Upload/eDoc/調查報告/100/100000355南海段國有房地-調查報告(對外).doc", 
    "describe": "陳委員健民調查：據訴渠前於民國40年間承購坐落臺北市中正區南海段3小段52地號等國有房地，業已給付原買賣契約價金，詎財政部國有財產局臺灣北區辦事處迄未辦理所有權移轉登記，損及權益等情乙案。....詳全文", 
    "reportLink": "", 
    "date": "100/08/03", 
    "pdf": "http://www.cy.gov.tw/AP_HOME/Op_Upload/eDoc/調查報告/100/100000355南海段國有房地-調查報告(對外).pdf", 
    "id": "1000800224"
  }, 
  {
    "docx": "http://www.cy.gov.tw/AP_HOME/Op_Upload/eDoc/調查報告/100/100000357石武雄-調查報告(對外).doc", 
    "describe": "黃委員煌雄、趙委員昌平調查：據李彥川陳訴，渠於93年8月22日任職財政部臺北關稅局外棧組期間，查獲疑似仿冒案件，通報權責股注意查驗；惟主管股長石武雄竟偽冒渠簽註同意退運，又該局明知上情，卻以渠無權簽註為由，予以議處，涉有違失等情乙案之調查報告。....詳全文", 
    "reportLink": "http://www.cy.gov.tw/sp.asp?xdUrl=./di/edoc/eDocForm_Read.asp&ctNode=911&AP_Code=eDoc&Func_Code=t02&case_id=100000135", 
    "date": "100/08/03", 
    "pdf": "http://www.cy.gov.tw/AP_HOME/Op_Upload/eDoc/調查報告/100/100000357石武雄-調查報告(對外).pdf", 
    "id": "1000800176"
  }, 
  {
    "docx": "http://www.cy.gov.tw/AP_HOME/Op_Upload/eDoc/調查報告/100/100000358高市場案調查報告.doc", 
    "describe": "劉委員興善調查：據審計部函報：稽察高雄市政府經濟發展局經管高雄市各公有市場之營運，暨該府都市發展局興建民權超級市場，涉有未盡職責及效能過低情事乙案之調查報告。....詳全文", 
    "reportLink": "", 
    "date": "100/08/03", 
    "pdf": "http://www.cy.gov.tw/AP_HOME/Op_Upload/eDoc/調查報告/100/100000358高市場案調查報告.pdf", 
    "id": "1000800014"
  }, 
  {
    "docx": "http://www.cy.gov.tw/AP_HOME/Op_Upload/eDoc/調查報告/100/100000351榮總績效獎金案調查意見（上網）.doc", 
    "describe": "劉委員玉山調查「『行政院國軍退除役官兵輔導委員會所屬榮民總醫院績效獎金分配方式與發給規定』似未臻健全，又臺北榮民總醫院前院長李良雄逕依前項規定核定自身績效獎金，疑違反公職人員利益衝突迴避法，涉有違失等情」之調查報告。....詳全文", 
    "reportLink": "", 
    "date": "100/07/21", 
    "pdf": "http://www.cy.gov.tw/AP_HOME/Op_Upload/eDoc/調查報告/100/100000351榮總績效獎金案調查意見（上網）.pdf", 
    "id": "1000800127"
  }, 
  {
    "docx": "http://www.cy.gov.tw/AP_HOME/Op_Upload/eDoc/調查報告/100/100000353上外網調查報告.doc", 
    "describe": "杜委員善良調查「據審計部函報：稽察行政院國軍退除役官兵輔導委員會所屬臺北榮民技術勞務中心承攬採購及經營績效情形，涉有未盡職責、效能過低及財務違失等情案。」之調查報告。....詳全文", 
    "reportLink": "", 
    "date": "100/07/21", 
    "pdf": "http://www.cy.gov.tw/AP_HOME/Op_Upload/eDoc/調查報告/100/100000353上外網調查報告.pdf", 
    "id": "0990801098"
  }, 
  {
    "docx": "http://www.cy.gov.tw/AP_HOME/Op_Upload/eDoc/調查報告/100/100000339勞保案調查報告-對外版.doc", 
    "describe": "劉委員玉山、馬委員秀如調查︰據審計部函報，勞工保險費率長期遠低於精算費率，且缺乏精算調整機制，又勞保老年給付標準逐步放寬，迭入不敷出，肇使勞工保險基金規模逐年遞減，將對社會安定產生重大衝擊乙案之調查報告。....詳全文", 
    "reportLink": "", 
    "date": "100/07/19", 
    "pdf": "http://www.cy.gov.tw/AP_HOME/Op_Upload/eDoc/調查報告/100/100000339勞保案調查報告-對外版.pdf", 
    "id": "0990800816"
  }, 
  {
    "docx": "http://www.cy.gov.tw/AP_HOME/Op_Upload/eDoc/調查報告/100/100000340楊林呅調查報告-對外版.doc", 
    "describe": "沈委員美真調查︰據楊林呅等陳訴，最高行政法院審理渠等與新北市政府稅捐稽徵處間土地增值稅事件，疑未詳查事證，率以99年度裁字第3197號裁定駁回再審之聲請，損及權益等情乙案之調查報告。....詳全文", 
    "reportLink": "", 
    "date": "100/07/19", 
    "pdf": "http://www.cy.gov.tw/AP_HOME/Op_Upload/eDoc/調查報告/100/100000340楊林呅調查報告-對外版.pdf", 
    "id": "1000800128"
  }, 
  {
    "docx": "http://www.cy.gov.tw/AP_HOME/Op_Upload/eDoc/調查報告/100/100000342面板案調查意見-公布.doc", 
    "describe": "李委員炳南自動調查︰國內面板廠友達遭歐美以反托拉斯法起訴，並將公司高階主管等人限制離境或處以鉅額之罰金；國內相關產業如奇美電、華映、翰宇彩晶等，皆面臨相似困境。對於外國相關司法措施，究外交部或經濟部等相關機關有無提供適當協助，以保護國民境外之人身自由或財產等權利，認有深入瞭解必要乙案之調查報告。....詳全文", 
    "reportLink": "", 
    "date": "100/07/19", 
    "pdf": "http://www.cy.gov.tw/AP_HOME/Op_Upload/eDoc/調查報告/100/100000342面板案調查意見-公布.pdf", 
    "id": "0990801073"
  }, 
  {
    "docx": "http://www.cy.gov.tw/AP_HOME/Op_Upload/eDoc/調查報告/100/100000346台電核四混凝土採購弊案調查報告（公告版）.doc", 
    "describe": "高委員鳳仙、陳委員永祥調查：據經濟部函送，台灣電力股份有限公司於87年間辦理「龍門計畫(核四)混凝土製造供應工程」採購案，核能火力發電工程處副研究員周吉村疑似收取廠商賄賂及不正利益，復與該處前副處長許仁勇及龍門核四施工處前副主任周芳國等3人浮報工程價額，均違反貪污治罪條例相關規定，涉有違失等情乙案之調查報告。....詳全文", 
    "reportLink": "http://www.cy.gov.tw/sp.asp?xdUrl=./di/edoc/eDocForm_Read.asp&ctNode=911&AP_Code=eDoc&Func_Code=t02&case_id=100000131", 
    "date": "100/07/19", 
    "pdf": "http://www.cy.gov.tw/AP_HOME/Op_Upload/eDoc/調查報告/100/100000346台電核四混凝土採購弊案調查報告（公告版）.pdf", 
    "id": "0990800916"
  }, 
  {
    "docx": "http://www.cy.gov.tw/AP_HOME/Op_Upload/eDoc/調查報告/100/100000349國華人壽調查報告核定版-對外.doc", 
    "describe": "李委員復甸、葉委員耀鵬調查：行政院金融監督管理委員會對於國華人壽保險股份有限公司及華山產物保險股份有限公司財務惡化，未即時採取監理措施，致衝擊保險金融秩序，涉有違失；復該會建構整體保險業之監理措施及退場機制是否周全，有無執行失當等情乙案之調查報告。....詳全文", 
    "reportLink": "http://www.cy.gov.tw/sp.asp?xdUrl=./di/edoc/eDocForm_Read.asp&ctNode=911&AP_Code=eDoc&Func_Code=t02&case_id=100000132", 
    "date": "100/07/19", 
    "pdf": "http://www.cy.gov.tw/AP_HOME/Op_Upload/eDoc/調查報告/100/100000349國華人壽調查報告核定版-對外.pdf", 
    "id": "0990800824"
  }, 
  {
    "docx": "http://www.cy.gov.tw/AP_HOME/Op_Upload/eDoc/調查報告/100/100000348漢翔案-調查報告(對外).doc", 
    "describe": "黃委員煌雄調查：據審計部函報，稽察漢翔航空工業股份有限公司辦理「沙鹿廠區飛航服務棚廠及停機坪籌建工程統包案」執行情形，涉有未盡職責及效能過低情事乙案之調查報告。....詳全文", 
    "reportLink": "", 
    "date": "100/07/19", 
    "pdf": "http://www.cy.gov.tw/AP_HOME/Op_Upload/eDoc/調查報告/100/100000348漢翔案-調查報告(對外).pdf", 
    "id": "1000800153"
  }, 
  {
    "docx": "http://www.cy.gov.tw/AP_HOME/Op_Upload/eDoc/調查報告/100/100000341豐原租金調查報告-對外版.doc", 
    "describe": "趙委員榮耀調查︰據訴，渠等持分共有台中市豐原區中正路199號7樓至地下1樓房屋，面積共990.29坪，月租金55萬元；詎財政部臺灣省中區國稅局未依法查明鄰近租金標準，逕以「平均租金」作為核課之依據，課以重稅，損及權益等情乙案之調查報告。....詳全文", 
    "reportLink": "", 
    "date": "100/07/19", 
    "pdf": "http://www.cy.gov.tw/AP_HOME/Op_Upload/eDoc/調查報告/100/100000341豐原租金調查報告-對外版.pdf", 
    "id": "1000800119"
  }, 
  {
    "docx": "http://www.cy.gov.tw/AP_HOME/Op_Upload/eDoc/調查報告/100/100000343阿里山小火車翻覆事故案調查意見-公布.doc", 
    "describe": "程委員仁宏、楊委員美鈴、黃委員武次、陳委員永祥自動調查︰據報載，100年4月27日阿里山小火車翻覆事件，肇因1棵森氏櫟樹斷裂，擊中其中1節車廂，導致4節車廂翻覆，造成5死113傷慘劇；又事故地點地形特殊，第1批救援隊於20分鐘之後才抵達。究主管機關對阿里山小火車之安全管理措施是否完善？邊坡養護與巡軌有無落實？鐵道淨空範圍是否合乎安全？緊急救難之相關配套措施是否周全？火車駕駛是否操作不當？及火車駕駛養成訓練機制為何？均有深入瞭解必要乙案之調查報告。....詳全文", 
    "reportLink": "http://www.cy.gov.tw/sp.asp?xdUrl=./di/edoc/eDocForm_Read.asp&ctNode=911&AP_Code=eDoc&Func_Code=t02&case_id=100000130", 
    "date": "100/07/19", 
    "pdf": "http://www.cy.gov.tw/AP_HOME/Op_Upload/eDoc/調查報告/100/100000343阿里山小火車翻覆事故案調查意見-公布.pdf", 
    "id": "1000800159"
  }, 
  {
    "docx": "http://www.cy.gov.tw/AP_HOME/Op_Upload/eDoc/調查報告/100/100000344金門自來水調查意見-公布.doc", 
    "describe": "周委員陽山、余委員騰芳自動調查︰金門地區受天候及環境限制，自來水供應嚴重不足，且水質日益惡化，中央主管機關迄今仍無積極對策，解決此一重大民生問題等情乙案之調查報告。....詳全文", 
    "reportLink": "", 
    "date": "100/07/19", 
    "pdf": "http://www.cy.gov.tw/AP_HOME/Op_Upload/eDoc/調查報告/100/100000344金門自來水調查意見-公布.pdf", 
    "id": "1000800103"
  }, 
  {
    "docx": "http://www.cy.gov.tw/AP_HOME/Op_Upload/eDoc/調查報告/100/100000345程建敏訴法官案調查意見（公告版）.doc", 
    "describe": "錢林委員慧君、李委員炳南調查：據訴：臺灣臺北地方法院檢察署偵辦程建敏告發臺灣臺北地方法院審理96年度勞簡上字第41號請求給付資遣費事件之承審法官枉法裁判案，未詳查事證，率予簽結，涉有違失等情乙案。....詳全文", 
    "reportLink": "", 
    "date": "100/07/19", 
    "pdf": "http://www.cy.gov.tw/AP_HOME/Op_Upload/eDoc/調查報告/100/100000345程建敏訴法官案調查意見（公告版）.pdf", 
    "id": "0990801119"
  }, 
  {
    "docx": "http://www.cy.gov.tw/AP_HOME/Op_Upload/eDoc/調查報告/100/100000347金門醫院案調查報告-對外.doc", 
    "describe": "黃委員武次調查：據訴：金門縣立醫院及國軍金門醫院醫師疑似長期施打管制藥品致病患上癮，前經控告醫師涉嫌業務過失傷害；詎福建金門地方法院率為無罪之判決，又福建高等法院金門分院竟上訴駁回，涉有違失等情乙案之調查報告。....詳全文", 
    "reportLink": "", 
    "date": "100/07/19", 
    "pdf": "http://www.cy.gov.tw/AP_HOME/Op_Upload/eDoc/調查報告/100/100000347金門醫院案調查報告-對外.pdf", 
    "id": "1000800095"
  }, 
  {
    "docx": "http://www.cy.gov.tw/AP_HOME/Op_Upload/eDoc/調查報告/100/100000350農藥調查報告-對外版.doc", 
    "describe": "程委員仁宏、楊委員美鈴自動調查︰據報載，台灣省農會附設各級農會農化廠僅擁有農藥製字之許可證，卻私自將其他廠商購買進口之成品農藥，標示為國內製造，涉嫌販售偽農藥，疑違反農藥管理法相關規定。究主管機關之把關及管理機制為何？有無怠忽職守致影響民眾安全與權益？均有深入瞭解之必要乙案之調查報告。....詳全文", 
    "reportLink": "http://www.cy.gov.tw/sp.asp?xdUrl=./di/edoc/eDocForm_Read.asp&ctNode=911&AP_Code=eDoc&Func_Code=t02&case_id=100000133", 
    "date": "100/07/19", 
    "pdf": "http://www.cy.gov.tw/AP_HOME/Op_Upload/eDoc/調查報告/100/100000350農藥調查報告-對外版.pdf", 
    "id": "1000800150"
  }
]